LICENSE
MANIFEST.in
README.rst
setup.py
cj/__init__.py
cj/cli.py
cj.egg-info/PKG-INFO
cj.egg-info/SOURCES.txt
cj.egg-info/dependency_links.txt
cj.egg-info/entry_points.txt
cj.egg-info/top_level.txt